{
    "key": "group_5f5fe07ba4e61",
    "title": "Triumph - Alert",
    "fields": [
        {
            "key": "field_5f5fe0a41a45c",
            "label": "Background Color",
            "name": "background_color",
            "type": "select",
            "instructions": "",
            "required": 1,
            "conditional_logic": 0,
            "wrapper": {
                "width": "",
                "class": "",
                "id": ""
            },
            "choices": {
                "primary": "Primary Color",
                "secondary": "Secondary Color",
                "accent": "Accent Color",
                "custom": "Custom Color"
            },
            "default_value": "secondary",
            "allow_null": 0,
            "multiple": 0,
            "ui": 0,
            "return_format": "value",
            "ajax": 0,
            "placeholder": ""
        },
        {
            "key": "field_600753f79af4a",
            "label": "Custom Color",
            "name": "custom_color",
            "type": "color_picker",
            "instructions": "",
            "required": 0,
            "conditional_logic": [
                [
                    {
                        "field": "field_5f5fe0a41a45c",
                        "operator": "==",
                        "value": "custom"
                    }
                ]
            ],
            "wrapper": {
                "width": "",
                "class": "",
                "id": ""
            },
            "default_value": "#00263e"
        },
        {
            "key": "field_5f5fe0d6760f9",
            "label": "Icon",
            "name": "icon",
            "type": "text",
            "instructions": "Add any FontAwesome icon here.  https:\/\/fontawesome.com\/icons?d=gallery",
            "required": 0,
            "conditional_logic": 0,
            "wrapper": {
                "width": "",
                "class": "",
                "id": ""
            },
            "default_value": "",
            "placeholder": "",
            "prepend": "",
            "append": "",
            "maxlength": ""
        }
    ],
    "location": [
        [
            {
                "param": "post_type",
                "operator": "==",
                "value": "alert"
            }
        ]
    ],
    "menu_order": 0,
    "position": "normal",
    "style": "default",
    "label_placement": "top",
    "instruction_placement": "label",
    "hide_on_screen": "",
    "active": true,
    "description": "",
    "modified": 1611093099
}